gofannon/__init__.py
gofannon/arxiv/__init__.py
gofannon/arxiv/get_article.py
gofannon/arxiv/search.py
gofannon/base/__init__.py
gofannon/base/adk_mixin.py
gofannon/base/bedrock.py
gofannon/base/langchain.py
gofannon/base/langflow.py
gofannon/base/llamastack.py
gofannon/base/mcp.py
gofannon/base/smol_agents.py
gofannon/basic_math/__init__.py
gofannon/basic_math/addition.py
gofannon/basic_math/division.py
gofannon/basic_math/exponents.py
gofannon/basic_math/multiplication.py
gofannon/basic_math/subtraction.py
gofannon/config.py
gofannon/file/__init__.py
gofannon/file/list_directory.py
gofannon/file/read_file.py
gofannon/file/write_file.py
gofannon/get_url_content/__init__.py
gofannon/get_url_content/get_url_content.py
gofannon/github/__init__.py
gofannon/github/clone_repo.py
gofannon/github/commit_file.py
gofannon/github/create_issue.py
gofannon/github/get_repo_contents.py
gofannon/github/list_issues.py
gofannon/github/list_repo_files.py
gofannon/github/pr_review_tool.py
gofannon/github/read_file.py
gofannon/github/read_issue.py
gofannon/github/search.py
gofannon/google_search/__init__.py
gofannon/google_search/google_search.py
gofannon/grant_query/__init__.py
gofannon/grant_query/grant_query.py
gofannon/headless_browser/__init__.py
gofannon/headless_browser/base.py
gofannon/headless_browser/headless_browser_get.py
gofannon/nasa/__init__.py
gofannon/nasa/apod.py
gofannon/nhsta/__init__.py
gofannon/open_notify_space/__init__.py
gofannon/open_notify_space/iss_locator.py
gofannon/orchestration/__init__.py
gofannon/orchestration/firebase_wrapper.py
gofannon/pdf_reader/__init__.py
gofannon/pdf_reader/pdf_reader.py
gofannon/reasoning/__init__.py
gofannon/reasoning/base.py
gofannon/reasoning/hierarchical_cot.py
gofannon/reasoning/sequential_cot.py
gofannon/reasoning/tree_of_thought.py
gofannon/simpler_grants_gov/__init__.py
gofannon/simpler_grants_gov/base.py
gofannon/simpler_grants_gov/get_opportunity.py
gofannon/simpler_grants_gov/list_agencies.py
gofannon-0.25.47.dist-info/METADATA
gofannon-0.25.47.dist-info/WHEEL
gofannon-0.25.47.dist-info/licenses/LICENSE
gofannon-0.25.47.dist-info/RECORD
