Metadata-Version: 2.4
Name: gofannon
Version: 0.25.47
Summary: A collection of tools for LLMs
License: ASFv2
License-File: LICENSE
Author: Trevor Grant
Author-email: trevor.d.grant@gmail.com
Requires-Python: >=3.10,<4.0
Classifier: License :: Other/Proprietary License
Classifier: Programming Language :: Python :: 3
Classifier: Programming Language :: Python :: 3.10
Classifier: Programming Language :: Python :: 3.11
Classifier: Programming Language :: Python :: 3.12
Classifier: Programming Language :: Python :: 3.13
Classifier: Programming Language :: Python :: 3.14
Provides-Extra: aws
Provides-Extra: google
Provides-Extra: headless-browser
Provides-Extra: langchain
Provides-Extra: langflow
Provides-Extra: pdf
Provides-Extra: smolagents
Provides-Extra: testing
Requires-Dist: GitPython (>=3.1.43,<4.0.0)
Requires-Dist: boto3 (>=1.34.97,<2.0.0) ; extra == "aws"
Requires-Dist: google-api-python-client (>=2.154.0,<3.0.0) ; extra == "google"
Requires-Dist: jsonschema (>=4.23.0,<5.0.0)
Requires-Dist: langchain-core (>=0.3.16,<0.4.0) ; (python_version < "3.13") and (extra == "langchain")
Requires-Dist: openai (>=1.60.2,<2.0.0)
Requires-Dist: pdfplumber (>=0.10.2,<0.11.0) ; extra == "pdf"
Requires-Dist: pydantic (>=2.10.6,<3.0.0) ; extra == "langchain"
Requires-Dist: pygithub (>=2.6.1,<3.0.0)
Requires-Dist: pytest (>=8.3.5,<9.0.0) ; extra == "testing"
Requires-Dist: python-dotenv (>=1.0.1,<2.0.0)
Requires-Dist: requests (>=2.32.3,<3.0.0)
Requires-Dist: requests-mock (>=1.12.1,<2.0.0) ; extra == "testing"
Requires-Dist: selenium (>=4.10.0,<5.0.0) ; extra == "headless-browser"
Requires-Dist: smolagents (>=1.6.0,<2.0.0) ; extra == "smolagents"
